portal_env/__init__.py
portal_env/agent_side_portal.py
portal_env/config.py
portal_env/docker_backend.py
portal_env/env_side_cli.py
portal_env/env_side_portal.py
portal_env/micromamba_backend.py
portal_env/utils.py
portal_env/envs/__init__.py
portal_env/envs/ale/Dockerfile.env
portal_env/envs/ale/__init__.py
portal_env/envs/ale/env_main.py
portal_env/envs/ale/spec.yml
portal_env/envs/craftium/Dockerfile.env
portal_env/envs/craftium/__init__.py
portal_env/envs/craftium/env_main.py
portal_env/envs/craftium/env_setup.py
portal_env/envs/craftium/spec.yml
portal_env/envs/flappy-bird/Dockerfile.env
portal_env/envs/flappy-bird/__init__.py
portal_env/envs/flappy-bird/env_main.py
portal_env/envs/flappy-bird/spec.yml
portal_env/envs/mujoco/Dockerfile.env
portal_env/envs/mujoco/__init__.py
portal_env/envs/mujoco/env_main.py
portal_env/envs/mujoco/spec.yml
portal_env/envs/retro/Dockerfile.env
portal_env/envs/retro/__init__.py
portal_env/envs/retro/env_main.py
portal_env/envs/retro/env_setup.py
portal_env/envs/retro/spec.yml
portal_env/envs/vizdoom/Dockerfile.env
portal_env/envs/vizdoom/__init__.py
portal_env/envs/vizdoom/env_main.py
portal_env/envs/vizdoom/spec.yml
portal_env-0.8.6.dist-info/licenses/LICENSE
portal_env-0.8.6.dist-info/METADATA
portal_env-0.8.6.dist-info/WHEEL
portal_env-0.8.6.dist-info/entry_points.txt
portal_env-0.8.6.dist-info/top_level.txt
portal_env-0.8.6.dist-info/RECORD
