Metadata-Version: 2.4
Name: portal-env
Version: 0.8.6
Summary: A package that simplifies RL development by conveniently running RL environments in isolated Docker containers, avoiding dependencies conflicts. The agent interacts with the isolated environment through a Gymnasium interface that functions as a relay.
Author-email: Leor Cohen <liorcohen5@campus.technion.ac.il>
License-Expression: MIT
Project-URL: Homepage, https://github.com/leor-c/portal-env
Project-URL: Repository, https://github.com/leor-c/portal-env.git
Classifier: Programming Language :: Python :: 3
Requires-Python: >=3.8
License-File: LICENSE
Requires-Dist: portal
Requires-Dist: gymnasium
Requires-Dist: click
Requires-Dist: numpy
Requires-Dist: pyyaml
Requires-Dist: wget
Requires-Dist: loguru
Dynamic: license-file
